printpkg/__init__.py
printpkg/texts.py
printpkg-0.2.dist-info/METADATA
printpkg-0.2.dist-info/WHEEL
printpkg-0.2.dist-info/top_level.txt
printpkg-0.2.dist-info/RECORD
