Metadata-Version: 2.4
Name: printpkg
Version: 0.2
Summary: A simple package to print predefined texts
Author: Your Name
Author-email: your.email@example.com
Requires-Dist: pyperclip>=1.8.0
Dynamic: author
Dynamic: author-email
Dynamic: requires-dist
Dynamic: summary
